fi_dialogue_agents/__init__.py
fi_dialogue_agents/agent.py
fi_dialogue_agents-0.0.11.dist-info/METADATA
fi_dialogue_agents-0.0.11.dist-info/WHEEL
fi_dialogue_agents-0.0.11.dist-info/licenses/LICENSE
fi_dialogue_agents-0.0.11.dist-info/RECORD
