Metadata-Version: 2.3
Name: fi_dialogue_agents
Version: 0.0.11
Summary: Design agents to compete on FI Dialogue
Project-URL: Homepage, https://github.com/pypa/fi_dialogue_agents
Project-URL: Issues, https://github.com/pypa/fi_dialogue_agents/issues
Author-email: FI <sebastinssanty@gmail.com>
License-File: LICENSE
Classifier: License :: OSI Approved :: MIT License
Classifier: Operating System :: OS Independent
Classifier: Programming Language :: Python :: 3
Requires-Python: >=3.8
Requires-Dist: flask-cors==5.0.0
Requires-Dist: flask-socketio==5.4.1
Requires-Dist: flask==3.0.3
Requires-Dist: pyngrok==7.2.0
